oslactionspotting/__init__.py
oslactionspotting/apis/__init__.py
oslactionspotting/apis/download_configtask.py
oslactionspotting/apis/evaluate/__init__.py
oslactionspotting/apis/evaluate/builder.py
oslactionspotting/apis/evaluate/evaluate.py
oslactionspotting/apis/evaluate/utils.py
oslactionspotting/apis/inference/__init__.py
oslactionspotting/apis/inference/builder.py
oslactionspotting/apis/inference/inference.py
oslactionspotting/apis/inference/utils.py
oslactionspotting/apis/visualize/__init__.py
oslactionspotting/apis/visualize/builder.py
oslactionspotting/apis/visualize/visualizer.py
oslactionspotting/core/__init__.py
oslactionspotting/core/trainer.py
oslactionspotting/core/loss/__init__.py
oslactionspotting/core/loss/builder.py
oslactionspotting/core/loss/calf.py
oslactionspotting/core/loss/ce.py
oslactionspotting/core/loss/combine.py
oslactionspotting/core/loss/nll.py
oslactionspotting/core/optimizer/__init__.py
oslactionspotting/core/optimizer/builder.py
oslactionspotting/core/scheduler/__init__.py
oslactionspotting/core/scheduler/builder.py
oslactionspotting/core/utils/__init__.py
oslactionspotting/core/utils/default_args.py
oslactionspotting/core/utils/io.py
oslactionspotting/core/utils/lightning.py
oslactionspotting/datasets/__init__.py
oslactionspotting/datasets/builder.py
oslactionspotting/datasets/frame.py
oslactionspotting/datasets/json.py
oslactionspotting/datasets/soccernet.py
oslactionspotting/datasets/utils.py
oslactionspotting/models/__init__.py
oslactionspotting/models/builder.py
oslactionspotting/models/contextaware.py
oslactionspotting/models/e2espot.py
oslactionspotting/models/learnablepooling.py
oslactionspotting/models/backbones/__init__.py
oslactionspotting/models/backbones/builder.py
oslactionspotting/models/heads/__init__.py
oslactionspotting/models/heads/builder.py
oslactionspotting/models/necks/__init__.py
oslactionspotting/models/necks/builder.py
oslactionspotting/models/necks/calf.py
oslactionspotting/models/necks/pooling.py
oslactionspotting-0.2.4.dist-info/LICENSE
oslactionspotting-0.2.4.dist-info/METADATA
oslactionspotting-0.2.4.dist-info/WHEEL
oslactionspotting-0.2.4.dist-info/top_level.txt
oslactionspotting-0.2.4.dist-info/RECORD
