Metadata-Version: 2.1
Name: oslactionspotting
Version: 0.2.4
Summary: Action Spotting SDK
Home-page: https://github.com/OpenSportsLab/OSL-ActionSpotting
Author: ['Silvio Giancola', 'Yassine Benzakour']
Author-email: ['silvio.giancola@kaust.edu.sa', 'yassine.benzakour@student.uliege.be']
License: MIT
Keywords: SoccerNet,SDK,Spotting,Football,Soccer,Video
Classifier: Development Status :: 3 - Alpha
Classifier: Intended Audience :: Developers
Classifier: Topic :: Software Development :: Build Tools
Classifier: License :: OSI Approved :: MIT License
Classifier: Programming Language :: Python :: 3
Classifier: Programming Language :: Python :: 3.8
Classifier: Programming Language :: Python :: 3.9
Classifier: Programming Language :: Python :: 3.10
Classifier: Programming Language :: Python :: 3.11
License-File: LICENSE
Requires-Dist: tqdm
Requires-Dist: SoccerNet
Requires-Dist: matplotlib
Requires-Dist: scikit-learn
Requires-Dist: mmengine
Requires-Dist: pytorch-lightning
Requires-Dist: numpy
Requires-Dist: opencv-python
Requires-Dist: moviepy
Requires-Dist: tabulate
Requires-Dist: timm
